wattrex_driver_ea/__init__.py
wattrex_driver_ea/__version__.py
wattrex_driver_ea/context.py
wattrex_driver_ea/drv_ea.py
wattrex_driver_ea-0.0.3.dist-info/LICENSE.txt
wattrex_driver_ea-0.0.3.dist-info/METADATA
wattrex_driver_ea-0.0.3.dist-info/WHEEL
wattrex_driver_ea-0.0.3.dist-info/top_level.txt
wattrex_driver_ea-0.0.3.dist-info/RECORD
